mclinux_zouz-3.0.1.data/purelib/MCMC/__init__.py
mclinux_zouz-3.0.1.data/purelib/MCMC/maxmumclique.so
mclinux_zouz-3.0.1.dist-info/LICENSE.txt
mclinux_zouz-3.0.1.dist-info/METADATA
mclinux_zouz-3.0.1.dist-info/WHEEL
mclinux_zouz-3.0.1.dist-info/top_level.txt
mclinux_zouz-3.0.1.dist-info/RECORD
