Metadata-Version: 2.1
Name: mclinux-zouz
Version: 3.0.1
Summary: Algotirhm to find maximalclique
Home-page: UNKNOWN
Author: UNKNOWN
Author-email: UNKNOWN
License: UNKNOWN
Platform: UNKNOWN
